MANIFEST.in
README.rst
setup.py
docs/HISTORY.txt
docs/LICENSE.GPL
docs/LICENSE.txt
ftw/__init__.py
ftw.keywordoverlay.egg-info/PKG-INFO
ftw.keywordoverlay.egg-info/SOURCES.txt
ftw.keywordoverlay.egg-info/dependency_links.txt
ftw.keywordoverlay.egg-info/entry_points.txt
ftw.keywordoverlay.egg-info/namespace_packages.txt
ftw.keywordoverlay.egg-info/not-zip-safe
ftw.keywordoverlay.egg-info/requires.txt
ftw.keywordoverlay.egg-info/top_level.txt
ftw/keywordoverlay/__init__.py
ftw/keywordoverlay/configure.zcml
ftw/keywordoverlay/profiles/default/cssregistry.xml
ftw/keywordoverlay/profiles/default/jsregistry.xml
ftw/keywordoverlay/profiles/default/metadata.xml
ftw/keywordoverlay/resources/common.css
ftw/keywordoverlay/resources/multiselect-plone.js
ftw/keywordoverlay/resources/ui.multiselect.css