Metadata-Version: 1.0
Name: ftw.keywordoverlay
Version: 1.2
Summary: Puts a nice overlay over Archetypes' default keywordwidget for plone.
Home-page: https://github.com/4teamwork/ftw.keywordoverlay
Author: 4teamwork GmbH
Author-email: mailto:info@4teamwork.ch
License: GPL2
Keywords: plone widget archetypes keyword jquery ftw keywordoverlay
Platform: UNKNOWN
Classifier: Framework :: Plone
Classifier: Framework :: Plone :: 4.0
Classifier: Framework :: Plone :: 4.1
Classifier: Intended Audience :: Developers
Classifier: License :: OSI Approved :: GNU General Public License (GPL)
Classifier: Programming Language :: Python
Classifier: Programming Language :: Python :: 2.6
Classifier: Topic :: Software Development :: Libraries :: Python Modules
